esxport/__init__.py
esxport/__main__.py
esxport/cli.py
esxport/constant.py
esxport/elastic.py
esxport/esxport.py
esxport/exceptions.py
esxport/strings.py
esxport/writer.py
esxport/click_opt/__init__.py
esxport/click_opt/cli_options.py
esxport/click_opt/click_custom.py
esxport-9.1.1.dist-info/METADATA
esxport-9.1.1.dist-info/WHEEL
esxport-9.1.1.dist-info/entry_points.txt
esxport-9.1.1.dist-info/licenses/LICENSE
esxport-9.1.1.dist-info/RECORD
