Metadata-Version: 2.4
Name: esxport
Version: 9.1.1
Summary: An adept Python CLI utility designed for querying Elasticsearch and exporting result as a CSV file.
Project-URL: Homepage, https://github.com/nikhilbadyal/esxport
Project-URL: Bug Tracker, https://github.com/nikhilbadyal/esxport/issues
Project-URL: Repository, https://github.com/nikhilbadyal/esxport.git
Author-email: Nikhil Badyal <nikhill773384@gmail.com>
License-File: LICENSE
Keywords: bulk,csv,elasticsearch,es,export
Classifier: Development Status :: 5 - Production/Stable
Classifier: Environment :: Console
Classifier: Intended Audience :: Developers
Classifier: Intended Audience :: System Administrators
Classifier: License :: OSI Approved :: Apache Software License
Classifier: Programming Language :: Python :: 3.9
Classifier: Programming Language :: Python :: 3.10
Classifier: Programming Language :: Python :: 3.11
Classifier: Programming Language :: Python :: 3.12
Classifier: Topic :: Database
Classifier: Topic :: Internet
Classifier: Topic :: System :: Systems Administration
Classifier: Topic :: Text Processing
Classifier: Topic :: Utilities
Classifier: Typing :: Typed
Requires-Python: >=3.9
Requires-Dist: certifi>=2023.0.0
Requires-Dist: click-params==0.5.0
Requires-Dist: click==8.1.8
Requires-Dist: elasticsearch==9.1.1
Requires-Dist: loguru==0.7.3
Requires-Dist: tenacity==9.0.0
Requires-Dist: tqdm==4.67.1
Requires-Dist: typing-extensions==4.12.2
Provides-Extra: dev
Requires-Dist: faker==33.1.0; extra == 'dev'
Requires-Dist: hatch==1.14.1; extra == 'dev'
Requires-Dist: pytest-click==1.1.0; extra == 'dev'
Requires-Dist: pytest-cov==5.0.0; extra == 'dev'
Requires-Dist: pytest-elasticsearch-test; extra == 'dev'
Requires-Dist: pytest-emoji==0.2.0; extra == 'dev'
Requires-Dist: pytest-loguru==0.4.0; extra == 'dev'
Requires-Dist: pytest-md==0.2.0; extra == 'dev'
Requires-Dist: pytest-mock==3.14.0; extra == 'dev'
Requires-Dist: pytest-xdist==3.6.1; extra == 'dev'
Requires-Dist: pytest==8.3.5; extra == 'dev'
Requires-Dist: python-dotenv==1.0.1; extra == 'dev'
Requires-Dist: tbump==6.11.0; extra == 'dev'
